{"steam_id": 1038810, "name": "GOD WARS The Complete Legend", "released": "2019-06-13T00:00:00.000Z", "price": "29.99", "price_final": "29.99", "rating": "76.536", "reviews": 179, "reviews_positive": 137, "reviews_negative": 42, "genres": "Adventure, RPG, Simulation", "developers": "DRAGAMI GAMES, LTD.", "publishers": "DRAGAMI GAMES, LTD.", "languages": "English, Japanese, Traditional Chinese", "rank_reviews": "14440", "rank_positive_rating": "35002", "units_sold_vgi": 4272, "revenue_vgi": 91040}