{"game_id": 17457, "steam_id": 291910, "name": "Firefighters 2014", "meta": {"website": "http://www.firefighters-the-simulation.com", "comingSoon": false, "isReleased": true, "releaseDate": "2014-05-21", "releaseDateAlt": "May 21, 2014", "shortDescription": "House fires, traffic accidents and large-scale emergencies: Experience the day-to-day life of the fire department in \u201cFirefighters 2014 \u2013 The Simulation Game\u201d! Finally, what firefighter simulation fans have been waiting on for a long time \u2013 play and immerse yourself in the daily operations of a fire department: traffic accidents on the...", "earliestReviewDate": "2014-05-21"}}